LICENSE
README.rst
setup.py
pfdo_run/__init__.py
pfdo_run/__main__.py
pfdo_run/pfdo_run.py
pfdo_run.egg-info/PKG-INFO
pfdo_run.egg-info/SOURCES.txt
pfdo_run.egg-info/dependency_links.txt
pfdo_run.egg-info/entry_points.txt
pfdo_run.egg-info/not-zip-safe
pfdo_run.egg-info/requires.txt
pfdo_run.egg-info/top_level.txt