Metadata-Version: 2.1
Name: pfdo-run
Version: 3.2.2
Summary: Run arbitrary CLI on each nested dir of an inputdir
Home-page: https://github.com/FNNDSC/pfdo_med2image
Author: FNNDSC
Author-email: dev@babymri.org
License: MIT
Platform: UNKNOWN
License-File: LICENSE
